.gitignore
MANIFEST.in
README.txt
setup.py
collective/__init__.py
collective.blog.feeds.egg-info/PKG-INFO
collective.blog.feeds.egg-info/SOURCES.txt
collective.blog.feeds.egg-info/dependency_links.txt
collective.blog.feeds.egg-info/entry_points.txt
collective.blog.feeds.egg-info/namespace_packages.txt
collective.blog.feeds.egg-info/not-zip-safe
collective.blog.feeds.egg-info/requires.txt
collective.blog.feeds.egg-info/top_level.txt
collective/blog/__init__.py
collective/blog/feeds/__init__.py
collective/blog/feeds/adapters.py
collective/blog/feeds/configure.zcml
collective/blog/feeds/fatsyndication.zcml
collective/blog/feeds/fatsyndication_adapters.py
collective/blog/feeds/feedsviewlet.pt
collective/blog/feeds/syndication.zcml
collective/blog/feeds/testaudio.mp3
collective/blog/feeds/testlogo.jpg
collective/blog/feeds/tests.py
collective/blog/feeds/version.txt
collective/blog/feeds/viewlets.py
docs/HISTORY.txt
docs/INSTALL.txt
docs/LICENSE.GPL
docs/LICENSE.txt