Metadata-Version: 1.1
Name: collective.blog.feeds
Version: 2.1
Summary: Provides several syndication feed types for standard folders.
Home-page: http://svn.plone.org/svn/collective/collective.blog.feeds
Author: Jarn AS
Author-email: info@jarn.com
License: GPL
Keywords: plone blog rss podcast feeds
Platform: UNKNOWN
Classifier: Framework :: Plone
Classifier: Framework :: Plone :: 4.0
Classifier: Framework :: Plone :: 4.1
Classifier: Framework :: Plone :: 4.2
Classifier: Framework :: Plone :: 4.3
Classifier: Programming Language :: Python
Classifier: Programming Language :: Python :: 2.6
Classifier: Programming Language :: Python :: 2.7
